argocd_python_client/__init__.py
argocd_python_client/api_client.py
argocd_python_client/configuration.py
argocd_python_client/exceptions.py
argocd_python_client/model_utils.py
argocd_python_client/rest.py
argocd_python_client/api/__init__.py
argocd_python_client/api/account_service_api.py
argocd_python_client/api/application_service_api.py
argocd_python_client/api/certificate_service_api.py
argocd_python_client/api/cluster_service_api.py
argocd_python_client/api/gpg_key_service_api.py
argocd_python_client/api/project_service_api.py
argocd_python_client/api/repo_creds_service_api.py
argocd_python_client/api/repository_service_api.py
argocd_python_client/api/session_service_api.py
argocd_python_client/api/settings_service_api.py
argocd_python_client/api/version_service_api.py
argocd_python_client/apis/__init__.py
argocd_python_client/model/__init__.py
argocd_python_client/model/account_account.py
argocd_python_client/model/account_accounts_list.py
argocd_python_client/model/account_can_i_response.py
argocd_python_client/model/account_create_token_request.py
argocd_python_client/model/account_create_token_response.py
argocd_python_client/model/account_token.py
argocd_python_client/model/account_update_password_request.py
argocd_python_client/model/application_application_patch_request.py
argocd_python_client/model/application_application_resource_response.py
argocd_python_client/model/application_application_rollback_request.py
argocd_python_client/model/application_application_sync_request.py
argocd_python_client/model/application_application_sync_window.py
argocd_python_client/model/application_application_sync_windows_response.py
argocd_python_client/model/application_log_entry.py
argocd_python_client/model/application_managed_resources_response.py
argocd_python_client/model/application_resource_actions_list_response.py
argocd_python_client/model/application_sync_options.py
argocd_python_client/model/applicationv1alpha1_env_entry.py
argocd_python_client-1.0.2.dist-info/LICENSE
argocd_python_client-1.0.2.dist-info/METADATA
argocd_python_client-1.0.2.dist-info/WHEEL
argocd_python_client-1.0.2.dist-info/top_level.txt
argocd_python_client-1.0.2.dist-info/RECORD
