Metadata-Version: 2.1
Name: argocd-python-client
Version: 1.0.2
Summary: Consolidate Services
Home-page: UNKNOWN
Author: OpenAPI Generator community
Author-email: team@openapitools.org
License: UNKNOWN
Keywords: OpenAPI,OpenAPI-Generator,Consolidate Services
Platform: UNKNOWN
Requires-Python: >=3.6
License-File: LICENSE
Requires-Dist: urllib3 (>=1.25.3)
Requires-Dist: python-dateutil
